chembl_webresource_client/__init__.py
chembl_webresource_client/elastic_client.py
chembl_webresource_client/http_errors.py
chembl_webresource_client/new_client.py
chembl_webresource_client/query.py
chembl_webresource_client/query_set.py
chembl_webresource_client/settings.py
chembl_webresource_client/singleton.py
chembl_webresource_client/spore_client.py
chembl_webresource_client/test_docs_examples.py
chembl_webresource_client/test_utils.py
chembl_webresource_client/tests.py
chembl_webresource_client/unichem.py
chembl_webresource_client/url_query.py
chembl_webresource_client/utils.py
chembl_webresource_client/scripts/__init__.py
chembl_webresource_client/scripts/chembl_act.py
chembl_webresource_client/scripts/chembl_ids.py
chembl_webresource_client/scripts/chembl_m2t.py
chembl_webresource_client/scripts/chembl_sim.py
chembl_webresource_client/scripts/chembl_sub.py
chembl_webresource_client/scripts/chembl_t2m.py
chembl_webresource_client/scripts/utils.py
chembl_webresource_client-0.10.9.dist-info/LICENSE
chembl_webresource_client-0.10.9.dist-info/METADATA
chembl_webresource_client-0.10.9.dist-info/WHEEL
chembl_webresource_client-0.10.9.dist-info/entry_points.txt
chembl_webresource_client-0.10.9.dist-info/top_level.txt
chembl_webresource_client-0.10.9.dist-info/RECORD
