Metadata-Version: 2.1
Name: chembl-webresource-client
Version: 0.10.9
Summary: Python client fot accessing ChEMBL webservices.
Home-page: https://www.ebi.ac.uk/chembl/api/data/docs
Author: Michal Nowotka, Eloy Felix
Author-email: chembl-help@ebi.ac.uk
License: Apache Software License
Classifier: Development Status :: 4 - Beta
Classifier: Intended Audience :: Developers
Classifier: License :: OSI Approved :: Apache Software License
Classifier: Operating System :: POSIX :: Linux
Classifier: Programming Language :: Python :: 3.8
Classifier: Programming Language :: Python :: 3.9
Classifier: Programming Language :: Python :: 3.10
Classifier: Programming Language :: Python :: 3.11
Classifier: Topic :: Scientific/Engineering :: Chemistry
License-File: LICENSE
Requires-Dist: urllib3
Requires-Dist: requests>=2.18.4
Requires-Dist: requests-cache~=1.2
Requires-Dist: easydict
